async_django_session/aiohttp.py
async_django_session/asyncpg.py
async_django_session/base_backend.py
async_django_session/databases.py
async_django_session/fastapi.py
async_django_session/session.py
async_django_session/starlette.py
async_django_session/utils.py
async_django_session-0.3.1.dist-info/METADATA
async_django_session-0.3.1.dist-info/WHEEL
async_django_session-0.3.1.dist-info/top_level.txt
async_django_session-0.3.1.dist-info/RECORD
