Metadata-Version: 2.1
Name: async-django-session
Version: 0.3.1
Summary: Django-compatible session for async frameworks
Home-page: https://github.com/imbolc/async_django_session
Author: Imbolc
Author-email: imbolc@imbolc.name
License: MIT
Platform: UNKNOWN
Classifier: Development Status :: 4 - Beta
Classifier: License :: OSI Approved :: MIT License
Classifier: Programming Language :: Python :: 3
Classifier: Operating System :: OS Independent
